hhu_python_tasks/.mypy_cache/.gitignore
hhu_python_tasks/.mypy_cache/3.12/@plugins_snapshot.json
hhu_python_tasks/.mypy_cache/3.12/_ast.data.json
hhu_python_tasks/.mypy_cache/3.12/_ast.meta.json
hhu_python_tasks/.mypy_cache/3.12/_codecs.data.json
hhu_python_tasks/.mypy_cache/3.12/_codecs.meta.json
hhu_python_tasks/.mypy_cache/3.12/_collections_abc.data.json
hhu_python_tasks/.mypy_cache/3.12/_collections_abc.meta.json
hhu_python_tasks/.mypy_cache/3.12/_decimal.data.json
hhu_python_tasks/.mypy_cache/3.12/_decimal.meta.json
hhu_python_tasks/.mypy_cache/3.12/_locale.data.json
hhu_python_tasks/.mypy_cache/3.12/_locale.meta.json
hhu_python_tasks/.mypy_cache/3.12/_thread.data.json
hhu_python_tasks/.mypy_cache/3.12/_thread.meta.json
hhu_python_tasks/.mypy_cache/3.12/_typeshed/__init__.data.json
hhu_python_tasks/.mypy_cache/3.12/_typeshed/__init__.meta.json
hhu_python_tasks/.mypy_cache/3.12/_typeshed/importlib.data.json
hhu_python_tasks/.mypy_cache/3.12/_typeshed/importlib.meta.json
hhu_python_tasks/.mypy_cache/3.12/_warnings.data.json
hhu_python_tasks/.mypy_cache/3.12/_warnings.meta.json
hhu_python_tasks/.mypy_cache/3.12/abc.data.json
hhu_python_tasks/.mypy_cache/3.12/abc.meta.json
hhu_python_tasks/.mypy_cache/3.12/attr/__init__.data.json
hhu_python_tasks/.mypy_cache/3.12/attr/__init__.meta.json
hhu_python_tasks/.mypy_cache/3.12/attr/_cmp.data.json
hhu_python_tasks/.mypy_cache/3.12/attr/_cmp.meta.json
hhu_python_tasks/.mypy_cache/3.12/attr/_typing_compat.data.json
hhu_python_tasks/.mypy_cache/3.12/attr/_typing_compat.meta.json
hhu_python_tasks/.mypy_cache/3.12/attr/_version_info.data.json
hhu_python_tasks/.mypy_cache/3.12/attr/_version_info.meta.json
hhu_python_tasks/.mypy_cache/3.12/attr/converters.data.json
hhu_python_tasks/.mypy_cache/3.12/attr/converters.meta.json
hhu_python_tasks/.mypy_cache/3.12/attr/exceptions.data.json
hhu_python_tasks/.mypy_cache/3.12/attr/exceptions.meta.json
hhu_python_tasks/.mypy_cache/3.12/attr/filters.data.json
hhu_python_tasks-0.20.5.dist-info/WHEEL
hhu_python_tasks-0.20.5.dist-info/entry_points.txt
hhu_python_tasks-0.20.5.dist-info/METADATA
hhu_python_tasks-0.20.5.dist-info/RECORD
