Metadata-Version: 2.3
Name: hhu-python-tasks
Version: 0.20.5
Summary: invoke-specific tasks for Python projects
Author: Detlef Lannert
Author-email: Detlef Lannert <lannert@hhu.de>
Classifier: Development Status :: 4 - Beta
Classifier: Intended Audience :: Developers
Classifier: License :: OSI Approved :: GNU General Public License v3 (GPLv3)
Classifier: Operating System :: POSIX :: Linux
Classifier: Programming Language :: Python :: 3
Classifier: Programming Language :: Python :: 3.11
Classifier: Programming Language :: Python :: 3.12
Classifier: Topic :: Software Development :: Build Tools
Classifier: Typing :: Typed
Requires-Dist: attrs
Requires-Dist: cattrs
Requires-Dist: cyclopts
Requires-Dist: fabric
Requires-Dist: invoke
Requires-Dist: msgspec
Requires-Dist: niquests
Requires-Dist: pyproject-parser
Requires-Dist: pyyaml
Requires-Dist: rich
Requires-Dist: semantic-version
Requires-Dist: uuid-extension>=0.2.0
Requires-Dist: uuid-utils
Requires-Dist: wheel-filename
Requires-Dist: xdg-base-dirs
Maintainer: Detlef Lannert
Maintainer-email: Detlef Lannert <lannert@hhu.de>
Requires-Python: >=3.11
